{"1": {"2": "0"}, "2": {"2": "0"}, "3": {"2": "0"}, "4": {"1": [{"7": {"1": {"1": "UCRlRW0CVZAZiCa8GnYaleSw", "2": 1}, "2": "DrewAshlynMua"}, "8": {"1": "167", "2": "16600", "3": "https://yt3.ggpht.com/ytc/AAUvwng7WTYJG6EFeWk4LuvhmcsYwwAGv1dPg97MnBafEA=s88-c-k-c0x00ffffff-no-rj"}}, {"7": {"1": {"1": "UC8xaIcidBMZ2dKQSTpyrtAg", "2": 1}, "2": "violet4151"}, "8": {"1": "107", "2": "29400", "3": "https://yt3.ggpht.com/ytc/AAUvwnjvQlBtHzJsB29bYACPsslegvUrX55fX_FVHw50=s88-c-k-c0x00ffffff-no-rj"}}, {"7": {"1": {"1": "UClTl0Gxcj0-7ytj1wkDFoXw", "2": 1}, "2": "BEYOND TRANS with Mardi"}, "8": {"1": "271", "2": "4860", "3": "https://yt3.ggpht.com/ytc/AAUvwngtgKpulKywoB2jm2vd22267HBXNq6uqdVV647qzg=s88-c-k-c0x00ffffff-no-rj"}}, {"7": {"1": {"1": "UCRipAFKci8iHAaOW8e3OSVg", "2": 1}, "2": "Jazmin Lee"}, "8": {"1": "45", "2": "26800", "3": "https://yt3.ggpht.com/ytc/AAUvwniMp_tTFnmnGp5jEurCituOWzEhTgihBdQ-lylY6os=s88-c-k-c0x00ffffff-no-rj"}}, {"7": {"1": {"1": "UC8UK0PnUs2WB6LHfR3Q7agw", "2": 1}, "2": "Suddenly Fem"}, "8": {"1": "22", "2": "13400", "3": "https://yt3.ggpht.com/ytc/AAUvwngJTqYDBwA8Xt5Nxn5M-c28lSpOKW538JcKcEv6=s88-c-k-c0x00ffffff-no-rj"}}, {"7": {"1": {"1": "UCvhxR6fuRcl9EeZrvKOEhiA", "2": 1}, "2": "Fox and Owl"}, "8": {"1": "110", "2": "16500", "3": "https://yt3.ggpht.com/ytc/AAUvwnjnqYurYXOItgRg09_QWcFIrP1BfIJrFhmGu_4TTQ=s88-c-k-c0x00ffffff-no-rj"}}, {"7": {"1": {"1": "UCvDqC5pFgnluM4jI7taa2ng", "2": 1}, "2": "Vnessa Sichelle"}, "8": {"1": "129", "2": "21700", "3": "https://yt3.ggpht.com/ytc/AAUvwnjZz-ADFj2C03XfQn3Bbjpmv44zHzWPZdiLR3Et2Q=s88-c-k-c0x00ffffff-no-rj"}}, {"7": {"1": {"1": "UCOPi_nPSgoAxnksaZ4HBnZA", "2": 1}, "2": "Gaiacrusher9"}, "8": {"1": "1396", "2": "6650", "3": "https://yt3.ggpht.com/ytc/AAUvwnhUNZQVhwLfmkVZgRNoVx0i1m9QR3ezmH-XnVu-=s88-c-k-c0x00ffffff-no-rj"}}, {"7": {"1": {"1": "UC-J5w2pAYDkBD-iLpcAZD7w", "2": 1}, "2": "About TG Life"}, "8": {"1": "10", "2": "1530", "3": "https://yt3.ggpht.com/ytc/AAUvwnhOze6bqcyrA4nLlh4EZnqvwqUC2MARhgaIq-e4=s88-c-k-c0x00ffffff-no-rj"}}, {"7": {"1": {"1": "UCV7sB_rVM8oxaXo_dc1s7FA", "2": 1}, "2": "jiyoonTV"}, "8": {"1": "97", "2": "15800", "3": "https://yt3.ggpht.com/ytc/AAUvwnhq6u1Rm2xyRQpoqIW7WhxZ4_mntAEsceKEMxAt=s88-c-k-c0x00ffffff-no-rj"}}, {"7": {"1": {"1": "UCa8lOb_-AP7ZlaAE5IGzk4g", "2": 1}, "2": "The Jerry Springer Show"}, "8": {"1": "3322", "2": "2390000", "3": "https://yt3.ggpht.com/ytc/AAUvwnhJQUTJkDzbtuY22cw2ixvJQ3g0pv1jG5aqEQOg=s88-c-k-c0x00ffffff-no-rj"}}, {"7": {"1": {"1": "UCob6KG-Z3yte-WtO2ApBEYg", "2": 1}, "2": "A Gringa Agora Sou Eu"}, "8": {"1": "156", "2": "72400", "3": "https://yt3.ggpht.com/ytc/AAUvwniZJ4wr9NO5ZmcaSVr47B0CjdVU5i77VDjOF6ityw=s88-c-k-c0x00ffffff-no-rj"}}, {"7": {"1": {"1": "UC473UF9ezt1veLuR821pqtQ", "2": 1}, "2": "MC Channel"}, "8": {"1": "39", "2": "11600", "3": "https://yt3.ggpht.com/ytc/AAUvwnjT0H4EQUtW3_z5W-qtMzEDuNswbqIdVso1BKuS=s88-c-k-c0x00ffffff-no-rj"}}, {"7": {"1": {"1": "UCRCE8Xk7-JH3h_m32rwSpJA", "2": 1}, "2": "Marisa"}, "8": {"1": "2129", "2": "2810", "3": "https://yt3.ggpht.com/ytc/AAUvwniGq0ZJS7p9jWfGOmfBS3HxRfL7eicuIPlPk5UZyg=s88-c-k-c0x00ffffff-no-rj"}}, {"7": {"1": {"1": "UCNMct4YPgw_ekB5ujAtMgtQ", "2": 1}, "2": "\uc9d1\uc624\ub9ac"}, "8": {"1": "51", "2": "2980", "3": "https://yt3.ggpht.com/ytc/AAUvwniLQJjTHpjYqewfLenj23xN-gSvCl23BFPrdHuvhw=s88-c-k-c0x00ffffff-no-rj"}}, {"7": {"1": {"1": "UCaKE8oWQyysyQ3tuO136Vjg", "2": 1}, "2": "Great Machinery"}, "8": {"1": "30", "3": "https://yt3.ggpht.com/ytc/AAUvwnhMf5c0ITqV7LhPB0ioRyH68O1wNZ1Oj3x9eXmS=s88-c-k-c0x00ffffff-no-rj"}}, {"7": {"1": {"1": "UCJk76Cx9__K1vtewxIRRVXQ", "2": 1}, "2": "\u0110\u1ea1t Vlog Test Max 1"}, "8": {"1": "183", "2": "18900", "3": "https://yt3.ggpht.com/ytc/AAUvwnhfzB0AvI694HtAe8n_dv77I3K6fTn5e19KRw=s88-c-k-c0x00ffffff-no-rj"}}, {"7": {"1": {"1": "UCtxJwD8--XLV3eZWjxfLrYw", "2": 1}, "2": "leandra furac\u00e3o"}, "8": {"1": "272", "2": "3880", "3": "https://yt3.ggpht.com/ytc/AAUvwniLudfrrjDA_jEpWX6KbyFdBCHFBl6Fi-OtUP_D0w=s88-c-k-c0x00ffffff-no-rj"}}, {"7": {"1": {"1": "UCd-lH7BznEptjcZ1Z7VcJvg", "2": 1}, "2": "tricksofthestrade"}, "8": {"1": "194", "2": "9380", "3": "https://yt3.ggpht.com/ytc/AAUvwniVg9ZJnldZetfKIVUu77N-WcVpE1mvX_sG5jUl=s88-c-k-c0x00ffffff-no-rj"}}, {"7": {"1": {"1": "UCAZNyeC6lFCttqzki3mxd3Q", "2": 1}, "2": "Andrey Sokolov"}, "8": {"1": "19", "2": "11000", "3": "https://yt3.ggpht.com/ytc/AAUvwnj0aGow_e3pNYZ_DNmje1zmZXW0sq7K6g04GHmV=s88-c-k-c0x00ffffff-no-rj"}}], "2": "107"}, "5": {"1": [{"1": "transsexual", "2": "", "3": "0", "4": ""}], "2": "1"}, "6": {"2": "0"}}