{"1": {"2": "0"}, "2": {"2": "0"}, "3": {"2": "0"}, "4": {"2": "0"}, "5": {"1": [{"1": "Q_Y4j8n-qYQ", "2": "&#39;I&#39;m relieved,&#39; community members react to VDARE conference cancellation", "3": "1186", "4": "KOAA 5"}, {"1": "fDKvdFLrENU", "2": "Peter Brimelow of VDare on How Republican Party Has to be More White", "3": "6061", "4": "TYT's The Conversation"}, {"1": "1RtlrXnyDZg", "2": "Michael Shure &amp; Wes Clark Jr Debate Conservative from VDARE", "3": "4530", "4": "TYT's The Conversation"}, {"1": "rVV2Vm5s4VI", "2": "Screw Blacks, Screw Women, White! White! White! Says Conservative Thinker", "3": "253154", "4": "The Young Turks"}, {"1": "uxeZ28jolZA", "2": "VDARE-iations on a Theme | The Facepalm Five: September 2, 2019", "3": "9392", "4": "Steve Shives"}, {"1": "O2iI1bakLGQ", "2": "Tancredo: Colorado GOP should have stuck up for VDARE conference", "3": "421", "4": "Next 9NEWS"}, {"1": "CcpnH9l06T4", "2": "Peter and Lydia Brimelow of VDARE.com after seeing the FERGUSON play", "3": "1801", "4": "The Ann and Phelim Scoop"}, {"1": "I4FjHVLF0NI", "2": "Trump&#39;s DOJ Busted Spreading White Supremacist Propaganda", "3": "142875", "4": "The Young Turks"}, {"1": "VTW3tNzRjNo", "2": "Emails Show Stephen Miller Promoted White Supremacist Content | The Last Word | MSNBC", "3": "187396", "4": "MSNBC"}, {"1": "0U3sZ_RigI8", "2": "Will immigrants harm America? (1995) | THINK TANK", "3": "1470", "4": "American Enterprise Institute"}, {"1": "uK4IKzToq5A", "2": "White Supremacy Defended By Former National Review Writer", "3": "40462", "4": "The Young Turks"}, {"1": "ADwKRjm_kF4", "2": "VDARE is Gone From YouTube", "3": "113", "4": "Blog of The W3st"}, {"1": "Pm4U3lmf58U", "2": "Chuck Wilder with Allan Wall VDARE.com", "3": "182", "4": "CRN Digital Talk Radio"}, {"1": "Gpua2feEUc8", "2": "Peter Brimelow Interviewed by Craig Bodeker", "3": "7774", "4": "Craig Bodeker"}, {"1": "P1UCNwJta3E", "2": "America&#39;s immigration disaster", "3": "573", "4": "Canoe"}, {"1": "x2uOLdQOEcc", "2": "Peter Brimelow: &quot;Immigration--Is This the Breaking Point?&quot; (2015)", "3": "17", "4": "American Renaissance Speeches"}, {"1": "G5tH2-f6CUM", "2": "Conservative: GOP Should Be More White", "3": "18850", "4": "Secular Talk"}, {"1": "mBRjUWoyqXM", "2": "European and Israeli Responses to Illegal Immigration", "3": "2954", "4": "Social Contract"}, {"1": "OjU0SdfHKBk", "2": "WE ARE DOOMED! John Derbyshire Interview", "3": "1822", "4": "HUSSAR"}, {"1": "YVFEwWGcLoQ", "2": "Gab Free Speech Radio Episode 11: VDARE YouTube Ban, Loomer Comcast Ban", "3": "430", "4": "Gab Free Speech Radio"}], "2": "299"}, "6": {}}