{"1": {"2": "0"}, "2": {"2": "0"}, "3": {"2": "0"}, "4": {"1": [{"7": {"1": {"1": "UCAwylBbx8RiRD3VsaYdwNTw", "2": 1}, "2": "Video Advice"}, "8": {"1": "143", "2": "2550000", "3": "https://yt3.ggpht.com/a/AATXAJzF-OiRAOC9WKU9FXPLFg-SRQmjwgKD_EdKGAr6eQ=s88-c-k-c0x00ffffff-no-rj"}}, {"7": {"1": {"1": "UCeIOGg90hHh2n1-UVQbiBoA", "2": 1}, "2": "ADVICE FOR GUYS"}, "8": {"1": "157", "2": "56900", "3": "https://yt3.ggpht.com/ytc/AAUvwnhK2gt2cPpX_cp8ZYyKdciCCIcnRNJ4_mWBqhhn=s88-c-k-c0x00ffffff-no-rj"}}, {"7": {"1": {"1": "UCff0OngpmLBrA187rPwA8Sg", "2": 1}, "2": "Kriszh Advice"}, "8": {"1": "662", "2": "227000", "3": "https://yt3.ggpht.com/ytc/AAUvwnhzd00ufee4asD5hzW2JJv15ervQ9xNbVVPez5-Vw=s88-c-k-c0x00ffffff-no-rj"}}, {"7": {"1": {"1": "UC9HGzFGt7BLmWDqooUbWGBg", "2": 1}, "2": "Matthew Hussey"}, "8": {"1": "555", "2": "2150000", "3": "https://yt3.ggpht.com/a/AATXAJyOjR3PlihbY3Hy2Tn08jHADvWEWgWNsmEgMa7hqA=s88-c-k-c0x00ffffff-no-rj"}}, {"7": {"1": {"1": "UC5TBTzLuvchdF9t8KE7zcfQ", "2": 1}, "2": "Auntie's Advice"}, "8": {"1": "831", "3": "https://yt3.ggpht.com/ytc/AAUvwng4h1HKf6RB6PE3STkS1nUAfxnNw1YYwLGgJo2GkA=s88-c-k-c0x00ffffff-no-rj"}}, {"7": {"1": {"1": "UC3ogrx6d9oohf6D42G44j1A", "2": 1}, "2": "Terrible Writing Advice"}, "8": {"1": "64", "2": "362000", "3": "https://yt3.ggpht.com/ytc/AAUvwnhQaPtqdJzwOySb_Pl5ijEwg68zyUBuiapenxJbYQ=s88-c-k-c0x00ffffff-no-rj"}}, {"7": {"1": {"1": "UChi-u2kNGiFIDhc5XKtWDDg", "2": 1}, "2": "Life Advice"}, "8": {"1": "31", "2": "94500", "3": "https://yt3.ggpht.com/ytc/AAUvwnizSBDgQpRpZaVSdFpzwRwK5uqQUV3uinXS4Y9P=s88-c-k-c0x00ffffff-no-rj"}}, {"7": {"1": {"1": "UClOZ-fMMvom8p2GWZ_ihpfw", "2": 1}, "2": "Love Advice TV"}, "8": {"1": "1096", "2": "283000", "3": "https://yt3.ggpht.com/a/AATXAJzr3xx4kIfaUsxvA9swcx5VxSp1DZXtSbm7sIWF=s88-c-k-c0x00ffffff-no-rj"}}, {"7": {"1": {"1": "UCHAeqYA43JwC2MQ0BbEEmPw", "2": 1}, "2": "Free Advice"}, "8": {"1": "364", "2": "609000", "3": "https://yt3.ggpht.com/a/AATXAJxAASZX_fKh6VwfYeyokE2AQuA9ZnEvmw9lMdHIpg=s88-c-k-c0x00ffffff-no-rj"}}, {"7": {"1": {"1": "UC_Ddf6gIbh-6E2uTC6U_h8Q", "2": 1}, "2": "Holley Carbs: How To's & Advice ,40 yrs of exp."}, "8": {"1": "26", "2": "3570", "3": "https://yt3.ggpht.com/a/AATXAJwlHGaAqUQjd1ckNFh9PO0HoZU0tS3Nw-dZP1Ni=s88-c-k-c0x00ffffff-no-rj"}}, {"7": {"1": {"1": "UCIWHHW-LwgauxPf1gb9kAig", "2": 1}, "2": "Advice from Dad"}, "8": {"1": "93", "2": "6450", "3": "https://yt3.ggpht.com/a/AATXAJxfgeyeGk-xOhtNPnMP_Yvnnrwf2Yr5Ljavdk3u=s88-c-k-c0x00ffffff-no-rj"}}, {"7": {"1": {"1": "UC8O9H2potmQyKfvU4JcKzqQ", "2": 1}, "2": "BBOY ONLINE"}, "8": {"1": "96", "2": "15600", "3": "https://yt3.ggpht.com/ytc/AAUvwnjILNXjkuSc9p3tQNy5J9aFHOS51Bn3xLpI2YhBFg=s88-c-k-c0x00ffffff-no-rj"}}, {"7": {"1": {"1": "UCVQRu2cTO7o1uiskhZLEwVw", "2": 1}, "2": "Auntie's Advice Channel For Women"}, "8": {"1": "167", "2": "7060", "3": "https://yt3.ggpht.com/a/AATXAJyKzebgMKOAH2NP3a5o6O7vZjIiWLRBIixvd7LX1w=s88-c-k-c0x00ffffff-no-rj"}}, {"7": {"1": {"1": "UCB4QWZLzUxNw8f9DTk5-QfQ", "2": 1}, "2": "NJ Advice"}, "8": {"1": "334", "3": "https://yt3.ggpht.com/a/AATXAJwZcedBsllNtXPsmhAUjcH6F6zpjC612JE2lfUhXA=s88-c-k-c0x00ffffff-no-rj"}}, {"7": {"1": {"1": "UCTbp93lrCC2Mtq9a9xvsljg", "2": 1}, "2": "V.P Advice"}, "8": {"1": "86", "3": "https://yt3.ggpht.com/a/AATXAJxxhei_B2tnkyR5HX_1BtGeEa-hS0CAp7yaxqmLvQ=s88-c-k-c0x00ffffff-no-rj"}}, {"7": {"1": {"1": "UCq8t12gtTboIYmne7ejMM2g", "2": 1}, "2": "Amaka's Advice"}, "8": {"1": "64", "2": "3970", "3": "https://yt3.ggpht.com/a/AATXAJyeffBuoGUsw61TWErXm7nJdIsnmdGfp5xo9e1b=s88-c-k-c0x00ffffff-no-rj"}}, {"7": {"1": {"1": "UCJDWauNlh3ltDEuQhlEUiCA", "2": 1}, "2": "Pro Advice"}, "8": {"1": "102", "2": "59100", "3": "https://yt3.ggpht.com/a/AATXAJyAV0lkVqu2EPJLW3iz07xYdwSErt8BSa7NKVEEyA=s88-c-k-c0x00ffffff-no-rj"}}, {"7": {"1": {"1": "UCbms2rFnpoYmL-D5u_6wzjQ", "2": 1}, "2": "Free Hindi Advice"}, "8": {"1": "536", "2": "55000", "3": "https://yt3.ggpht.com/ytc/AAUvwngzudNuj9mcYTrox1N4KXokYAhuAcw1vPF0iihX=s88-c-k-c0x00ffffff-no-rj"}}, {"7": {"1": {"1": "UCjTMOi3cpslA7JUmPdfD6MQ", "2": 1}, "2": "Tripp Advice"}, "8": {"1": "911", "2": "890000", "3": "https://yt3.ggpht.com/a/AATXAJzNdjxEu-2ffSno7h1tOgQJ6Cc4LVs2gT1xxUkfLQ=s88-c-k-c0x00ffffff-no-rj"}}, {"7": {"1": {"1": "UCcL9spxJvF7ET57igXURwOw", "2": 1}, "2": "Matthew Coast - Relationship Advice"}, "8": {"1": "559", "2": "197000", "3": "https://yt3.ggpht.com/a/AATXAJwWfMNrBSR_OMEw-xucuPFKe-EmrQWbs-j7m9SQ-A=s88-c-k-c0x00ffffff-no-rj"}}], "2": "672740"}, "5": {"1": [{"1": "GCU5ljQaIN4", "2": "Cadet x Deno - Advice (Dele Alli) [Music Video] | GRM Daily", "3": "39524824", "4": "GRM Daily"}, {"1": "fcBS5F9gei0", "2": "Cadet x Deno Driz - Advice (Dele Alli) (Lyrics)", "3": "3693878", "4": "UK Lyrics"}, {"1": "wqEsTPaUZF0", "2": "Jordan Peterson&#39;s Life Advice Will Change Your Future (MUST WATCH)", "3": "6927677", "4": "Motivation Madness"}, {"1": "A1waZCoYbts", "2": "Kehlani - Advice (Official Audio)", "3": "4192923", "4": "Kehlani"}, {"1": "7px5RuO_I5Q", "2": "relationship advice from the big sister you never had", "3": "122286", "4": "Hannah Elise"}, {"1": "JhckVlgYZJE", "2": "A old man&#39;s advice", "3": "5366086", "4": "Bernard Albertson"}, {"1": "_uGwCTRr8CQ", "2": "Important Life Advice No One Tells Young Women", "3": "284116", "4": "The Feminine Fancy"}, {"1": "rR5GkTnsSUk", "2": "TATLONG ADVICE NA HINDI KO NA IBIBIGAY SA IBA | Marcelo Santos III", "3": "21592", "4": "Marcelo TV"}, {"1": "k0jc0Pjn6QQ", "2": "Before You Give Up, Watch This | Life Advice Will Change Your Future | Pray Like Elijah", "3": "56594", "4": "Lion of Judah"}, {"1": "jyLFl-O3L0g", "2": "70 People Ages 5-75: Advice For Someone Younger Than You? | Glamour", "3": "4397011", "4": "Glamour"}, {"1": "eHpg8iyvPew", "2": "Femz20 -  Advice (Music Video) | @MixtapeMadness", "3": "25153", "4": "Mixtape Madness"}, {"1": "jUzxY3rgbkI", "2": "Will Smith&#39;s Life Advice Will Change You - One of the Greatest Speeches Ever | Will Smith Motivation", "3": "2676071", "4": "MotivationHub"}, {"1": "hJRgprjMdWo", "2": "AVEYRO AVE - ADVICE ft. RED", "3": "1258500", "4": "AVEYRO AVE"}, {"1": "_-4XtP-ysSg", "2": "What&#39;s The Single BEST Piece Of Advice You&#39;ve Ever Heard? (r/AskReddit)", "3": "106687", "4": "Best Posts & Comments"}, {"1": "b-LTA85deuk", "2": "Jack Ma&#39;s Advice For Young People", "3": "2962562", "4": "The Outcome"}, {"1": "BnSyg-sjViw", "2": "Incredible LIFE ADVICE From An Old Wise Man (very powerful)", "3": "154581", "4": "Be Inspired"}, {"1": "LZeUnDrXfHQ", "2": "REALEST advice for teen girls you will ever hear.", "3": "1046754", "4": "The Di'Amore Family"}, {"1": "vnEf8z1aZns", "2": "Denzel Washington&#39;s Life Advice Will Leave You SPEECHLESS (ft. Will Smith) | Eye Opening Speeches", "3": "10317793", "4": "MotivationHub"}, {"1": "lYGGpc2mMno", "2": "Jack Ma&#39;s Life Advice Will Change Your Life (MUST WATCH)", "3": "8895163", "4": "Motivation Madness"}, {"1": "LI6PJkLuE88", "2": "\u0b89\u0ba9\u0b95\u0bcd\u0b95\u0bc1 \u0ba8\u0bb2\u0bcd\u0bb2 \u0b9a\u0bc6\u0baf\u0bcd\u0ba4\u0bbf \u0bb5\u0bb0 \u0baa\u0bcb\u0b95\u0bbf\u0bb1\u0ba4\u0bc1 / Shirdi Sai Baba Advice in Tamil || Motivational Speech", "3": "4280", "4": "Mythily's Lifestyle"}], "2": "30662062"}, "6": {}}