{"1": {"1": [{"1": "online-tech-tips.com", "4": "4.5M - 5M"}, {"1": "techhive.com", "4": "4M - 4.5M"}, {"1": "magazine.calcalistech.com", "4": "20M - 25M"}, {"1": "thewiredshopper.com", "4": "500K - 1M"}, {"1": "infoworld.com", "4": "1M - 1.5M"}, {"1": "malayalam.gizbot.com", "4": "1.5M - 2M"}, {"1": "t3.com", "4": "20M - 25M"}, {"1": "techwalls.com", "4": "250K - 300K"}, {"1": "infotechnology.com", "4": "10M - 15M"}, {"1": "techxplore.com::Science X Network content pages, Multiple locations", "4": "300K - 350K"}, {"1": "slashgear.com::Tech article right under stories, Multiple locations", "4": "450K - 500K"}, {"1": "geekzone.co.nz::All pages, Top right", "4": "100K - 150K"}, {"1": "techsiting.com", "4": "150K - 200K"}, {"1": "techexpert.tips", "4": "1M - 1.5M"}, {"1": "onecomputerguy.com", "4": "250K - 300K"}, {"1": "techdifferences.com", "4": "350K - 400K"}, {"1": "carbiketech.com", "4": "500K - 1M"}, {"1": "bgr.in", "4": "5M - 10M"}, {"1": "tech-recipes.com", "4": "350K - 400K"}, {"1": "techexplorist.com", "4": "150K - 200K"}], "2": "235"}, "2": {"1": [{"2": "Tech News", "4": "Pinenuts Android Developers", "5": "https://lh3.googleusercontent.com/3PFAoj-v_3KEZvAKfyNRl7BOh9Bci9plIb065jyVO3eav8gPHnn8TViAnUFziGt91pZ4UOUz", "6": {"1": "it.pinenuts.technews", "2": 2}}, {"2": "Tech News & Reviews - VR, Drones, Startups & More", "4": "Newsfusion", "5": "https://lh3.googleusercontent.com/dpcH4YIa8ZpT33Yb5Yi4-teLcadzpXYxgdm0lx6hly7Es9M4Tk8wXyCT2HTwUbjk3sdxzGnIbOA", "6": {"1": "com.briox.riversip", "2": 2}}, {"2": "Tech News", "4": "Baris Efe", "5": "https://lh3.googleusercontent.com/E56FeohX1gw4hz6U8ehakl8IhXbEHqRxI77_aJFUCWnRbSxB_2iToyYPOeASBUDgeCeRBVV79Q", "6": {"1": "com.barisefe.technews", "2": 2}}, {"2": "Technology News", "4": "M-Media Soft", "5": "https://lh3.googleusercontent.com/cmKnzB417kmrBDbO_RsuLtE4790tX2kTOxqg7Q-uIaqZiEJ0inC1c1D32ypGJP5N9qQ94RyNZQ", "6": {"1": "com.technologynews.husni", "2": 2}}, {"2": "Toot", "4": "Showhowto Learning Media Pvt Ltd", "5": "https://lh3.googleusercontent.com/Ug4xC9l31b328_yiODreXeppCNI-tbiv2llUDE5aThLrRYKM6Q93hy1o0hlOFkHpcjbSaeCamNo", "6": {"1": "com.showhow2.toot.app", "2": 2}}, {"2": "Tech News", "4": "Khalid Android", "5": "https://lh3.googleusercontent.com/R3fbFWBRTjX1XSh9fg-6afRFVRiuhW4k8PfMu5Im3NNRX7W19HLdV0rxMDjm8aUZ2zzkfdZUUw", "6": {"1": "com.khalid.android.technews2020", "2": 2}}, {"2": "Tech News by Newsfusion", "4": "Newsfusion Ltd.", "5": "https://lh3.googleusercontent.com/yYHjFxc8ICZZD0n3nO87QPm_crMrGQ2ZlRztOWFH1knkLuemhGlOfA-Llk092pSAKaqBIDaFRA", "6": {"1": "451723649", "2": 1}}, {"2": "Tech News", "4": "lovelygroup", "5": "https://lh3.googleusercontent.com/riSdSsA-ApGuzx2ol0G9Ok8Gbl5kLP8Gef2eOZLRE2XtevyVCcXDagSfM1JTaqAn6xEWysfQ", "6": {"1": "com.passall.technews", "2": 2}}, {"2": "Tech News", "4": "iMobaio", "5": "https://lh3.googleusercontent.com/xJJJ2Nocmb22BPU6YndxbPN8FhLKZYBIcuJ8pJHhQveDHDQpAJcHdX_4D9ZR942fSQ3f-5gP1Q", "6": {"1": "com.imobaio.android.apps.technewsapp", "2": 2}}, {"2": "ALikeMe - Look Like Me", "4": "hello.ai.app", "5": "https://lh3.googleusercontent.com/htyKtSZECL7lIskb5ROyeJiP3fBd9LssVvFKjsqAG9Xc5TH8rtcSRAElioefEvn1pNbbi1Yh_g", "6": {"1": "com.celebrity.look.like.me", "2": 2}}, {"2": "Tech News Tube", "4": "GlassWave LLC", "5": "https://lh3.googleusercontent.com/kEwz_ahpqHvZWS7hzR7NlImC09MW4aN-znZzjp-LDOFuKP0N0UPos49wlIhQEEMF341vQcRo", "6": {"1": "422953518", "2": 1}}, {"2": "Technology News", "4": "M-Media Soft", "5": "https://lh3.googleusercontent.com/AxTduKVpERrebTGjWUPKHDhjy7VfV3B5Me5dw0ad5VgHux9IG7XbB8jY4wY_YLBTXblxDbLqsYA", "6": {"1": "com.tecnology.husni", "2": 2}}, {"2": "rockXradio", "4": "Nobex Technologies", "5": "https://lh3.googleusercontent.com/jOxUJNgODBySU4ZBQ3raYoHTwr0iYYTk1kbALBMv_EdXgYl67aAz9nib6rR-5Mke-CT8MjGi8Q", "6": {"1": "com.nobexinc.wls_59311174.rc", "2": 2}}, {"2": "Geek Tech - Actualit\u00e9s HighTech", "4": "GeekTech", "5": "https://lh3.googleusercontent.com/foB9y5JLNnmSqfPq3_NcNCZcNqxJEpYII8CrjrVJTQDFrlWITNWEkEZRBm3znpGtWzgxbYamNg", "6": {"1": "geektech.technewsapp", "2": 2}}, {"2": "Moviepad - Watch Movies", "4": "DeepQ", "5": "https://lh3.googleusercontent.com/agunOI-kgAoT-3TsRWSgeNhI45OKdi3E4ZE2uvhJQmtNhxD_dmy46p-EmW8gfoN8zxanDXvhAw", "6": {"1": "com.deepq.moviepad", "2": 2}}, {"2": "Khmer Song | Khmer Music", "4": "Wecambo Technology", "5": "https://lh3.googleusercontent.com/XW1rIBbQMi2ptdEA0zLL7WkxDgHlbQUzvvPVJFSlEa0veBoHLpkh1J8s1tgouWFm4z5CjghGAA", "6": {"1": "com.wecambo.musicmobile", "2": 2}}, {"2": "Alpha Tech Titan Racing Free", "4": "Xiangning Xu", "5": "https://lh3.googleusercontent.com/dd_zMq6AUEIpxo8KZRjHE-jA_Ii9mYQDiBQC_mMMQ8Oo7CurWTiP1_6yuFAsiu_GHXE4uAheUKg", "6": {"1": "823434745", "2": 1}}, {"2": "Gadget News", "4": "TIRALCODES", "5": "https://lh3.googleusercontent.com/EFCnP06YehA1OVRPyCO-Ne34_S5-k5vCHenhwdrdEWI0WkmAKhWMBDB9pbh6rWYiLCDbSGgEJQ", "6": {"1": "com.tiralcodes.gadget", "2": 2}}, {"2": "Blind - Workplace Community", "4": "Teamblind inc", "5": "https://lh3.googleusercontent.com/xjRLTBZ16kApge-LQMwUUhGFjFVorpYEHbFsSGPa7Wo9yOTPFhQkmCclLlFihWa5tKhzjyfS", "6": {"1": "737534965", "2": 1}}, {"2": "Actu Geek - News, Podcats, Vid\u00e9os Tech et Geek", "4": "AppyVid", "5": "https://lh3.googleusercontent.com/YjBYWk_ILncBTI2Np-uBQ8OjXlxA3fFsUBAG_0Rl62QmKi5nz-wmD3w1Ol2HC1g9QGVe_sHY", "6": {"1": "com.appyvid.actugeek", "2": 2}}], "2": "499"}, "3": {"2": "0"}, "4": {"1": [{"7": {"1": {"1": "UCBJycsmduvYEL83R_U4JriQ", "2": 1}, "2": "Marques Brownlee"}, "8": {"1": "1295", "2": "12900000", "3": "https://yt3.ggpht.com/ytc/AAUvwnhoa6jtz7ccGj30Al2Ha8t4ImDVW2U98STxoLXp=s88-c-k-c0x00ffffff-no-rj"}}, {"7": {"1": {"1": "UCagoIYmo_gO1iVaCeeSikEg", "2": 1}, "2": "This Week in Tech"}, "8": {"1": "411", "2": "39100", "3": "https://yt3.ggpht.com/a/AATXAJz0ib5b_Tu7GABLr2LaI5S5ZCK-vTN9AoB9VMbH=s88-c-k-c0x00ffffff-no-rj"}}, {"7": {"1": {"1": "UC9fSZHEh6XsRpX-xJc6lT3A", "2": 1}, "2": "UrAvgConsumer"}, "8": {"1": "892", "2": "3030000", "3": "https://yt3.ggpht.com/a/AATXAJy-zA1Z6zXEyjWB_IwS_rX9jLfKtMlYdNx9cIxUzg=s88-c-k-c0x00ffffff-no-rj"}}, {"7": {"1": {"1": "UCFfCqe7b9YiDk2ZiAG8UIGA", "2": 1}, "2": "Flossy Carter"}, "8": {"1": "2130", "2": "1590000", "3": "https://yt3.ggpht.com/ytc/AAUvwniS0D0RBQwWyPw9bit2M6SQhAllSXO_PsdG40tC2A=s88-c-k-c0x00ffffff-no-rj"}}, {"7": {"1": {"1": "UC4xKdmAXFh4ACyhpiQ_3qBw", "2": 1}, "2": "TechLead"}, "8": {"1": "224", "2": "894000", "3": "https://yt3.ggpht.com/ytc/AAUvwniAIuJTf8tYaEkS8CxoEtSi04EvKpr3ou1tTKLFkg=s88-c-k-c0x00ffffff-no-rj"}}, {"7": {"1": {"1": "UCV0qA-eDDICsRR9rPcnG7tw", "2": 1}, "2": "Joma Tech"}, "8": {"1": "80", "2": "719000", "3": "https://yt3.ggpht.com/ytc/AAUvwniqkVXvK9dEpAu9Mkpyz46oCwFYOgg5ummDXx0c=s88-c-k-c0x00ffffff-no-rj"}}, {"7": {"1": {"1": "UCD8fxc8DbCCa5auyaJIluBA", "2": 1}, "2": "BLACK N WHITE TECH"}, "8": {"1": "18", "2": "2970", "3": "https://yt3.ggpht.com/ytc/AAUvwniFne6oZHgZCyAMpOjFHaOX7jVwwmhpDxst4iDBQQ=s88-c-k-c0x00ffffff-no-rj"}}, {"7": {"1": {"1": "UCCss3QxegBkF8BAetIo0qXA", "2": 1}, "2": "Tech Deals"}, "8": {"1": "1642", "2": "472000", "3": "https://yt3.ggpht.com/ytc/AAUvwng6aiJ9UVj0GIFsoCBR6OtuEkxhG0Fnsoin5VqpXA=s88-c-k-c0x00ffffff-no-rj"}}, {"7": {"1": {"1": "UCE5dIscvDxrb7CD5uiJJOiw", "2": 1}, "2": "Adrian's Digital Basement"}, "8": {"1": "277", "2": "90400", "3": "https://yt3.ggpht.com/a/AATXAJw_YM3ESig-aBFbkI48XJGbWaiMINJnMdS2z8Qn=s88-c-k-c0x00ffffff-no-rj"}}, {"7": {"1": {"1": "UCCjyq_K1Xwfg8Lndy7lKMpA", "2": 1}, "2": "TechCrunch"}, "8": {"1": "8707", "2": "484000", "3": "https://yt3.ggpht.com/ytc/AAUvwnjNoj_bPAj-Dj0dMbtEano-nFMTvIoKSWGKDbIBgPQ=s88-c-k-c0x00ffffff-no-rj"}}, {"7": {"1": {"1": "UCjgpFI5dU-D1-kh9H1muoxQ", "2": 1}, "2": "Hacksmith Industries"}, "8": {"1": "657", "2": "10900000", "3": "https://yt3.ggpht.com/ytc/AAUvwni4Pd7D8nyy-OlF-6jy1R4nyuFV7NymZMjEp0dBVg=s88-c-k-c0x00ffffff-no-rj"}}, {"7": {"1": {"1": "UCLr4hMhk_2KE0GUBSBrspGA", "2": 1}, "2": "Kuba Klawiter"}, "8": {"1": "447", "2": "798000", "3": "https://yt3.ggpht.com/a/AATXAJzc-jb3TI61wUinIevqQbESlJ2lSH-WacauGvV_=s88-c-k-c0x00ffffff-no-rj"}}, {"7": {"1": {"1": "UCXuqSBlHAE6Xw-yeJA0Tunw", "2": 1}, "2": "Linus Tech Tips"}, "8": {"1": "5172", "2": "12400000", "3": "https://yt3.ggpht.com/a/AATXAJwQoPNwqUbfu_y7o7GWaeZgX8ovoHSYuWfbiJLR8g=s88-c-k-c0x00ffffff-no-rj"}}, {"7": {"1": {"1": "UCvVhBidV5kG4G58AVemMDsw", "2": 1}, "2": "Tech for Techs"}, "8": {"1": "303", "2": "7180", "3": "https://yt3.ggpht.com/ytc/AAUvwnhzQJRUG0XEgp0hVcE6lm1TUY2fB4s_u7h95EdF=s88-c-k-c0x00ffffff-no-rj"}}, {"7": {"1": {"1": "UCLx053rWZxCiYWsBETgdKrQ", "2": 1}, "2": "LGR"}, "8": {"1": "1092", "2": "1430000", "3": "https://yt3.ggpht.com/a/AATXAJy3cElHyxMxnrur2HKbGZQJe0OoElKQ3LhEMIGnVg=s88-c-k-c0x00ffffff-no-rj"}}, {"7": {"1": {"1": "UCTzLRZUgelatKZ4nyIKcAbg", "2": 1}, "2": "Hardware Canucks"}, "8": {"1": "1716", "2": "1520000", "3": "https://yt3.ggpht.com/a/AATXAJzfW0d0E8LW1bxMb_fj1UccQlbvXMhVmSm8sb2IZw=s88-c-k-c0x00ffffff-no-rj"}}, {"7": {"1": {"1": "UCRYOj4DmyxhBVrdvbsUwmAA", "2": 1}, "2": "Optimum Tech"}, "8": {"1": "414", "2": "382000", "3": "https://yt3.ggpht.com/a/AATXAJwVudGxH5JeOYJcVACv-8LFUlSchbH5zMuyf5VUZw=s88-c-k-c0x00ffffff-no-rj"}}, {"7": {"1": {"1": "UC0vBXGSyV14uvJ4hECDOl0Q", "2": 1}, "2": "Techquickie"}, "8": {"1": "807", "2": "3650000", "3": "https://yt3.ggpht.com/ytc/AAUvwnhjeYw4ML_pitqpnhOBgK2aNWGb5yJdAZvzaXxg=s88-c-k-c0x00ffffff-no-rj"}}, {"7": {"1": {"1": "UCPunhrO_o0Eapp7G4-LTg8w", "2": 1}, "2": "Black Tech Official"}, "8": {"1": "64", "2": "1670", "3": "https://yt3.ggpht.com/a/AATXAJwnDI1JMmLCAiozV7hE5__zT1IgXZbNbYhVSHZOVw=s88-c-k-c0x00ffffff-no-rj"}}, {"7": {"1": {"1": "UCzzY0ro-Kr3S1C0vhjhkZ4w", "2": 1}, "2": "NOBA TECH"}, "8": {"1": "217", "2": "43000", "3": "https://yt3.ggpht.com/a/AATXAJx634w_1LNuLi7WOBKwKCIIb38vf1jwtnfQE2dT=s88-c-k-c0x00ffffff-no-rj"}}], "2": "287600"}, "5": {"1": [{"1": "_1hdmagFPR4", "2": "Tech Industry Fuels Reverse Migration For Black Americans | NBC Nightly News", "3": "23667", "4": "NBC News"}, {"1": "Zoog7MdcAMw", "2": "WHY There Are NO Black Software Engineers", "3": "25626", "4": "Dummy Codes"}, {"1": "tPlokEjpk1o", "2": "Being Black in Technology", "3": "500", "4": "Tech Gee"}, {"1": "DUjm968ufnw", "2": "Tea with Bree #1 - On Being A Black Woman in Tech", "3": "1311", "4": "Bree Hall"}, {"1": "dcM5Y_BXjQY", "2": "18 Black Women in Tech You Need to Follow", "3": "3007", "4": "Coding Blonde"}, {"1": "oejOtgPDkLU", "2": "Dawn Dickson Talks The Black Tech Community, Breaking Barriers In Black Business + More", "3": "177222", "4": "Breakfast Club Power 105.1 FM"}, {"1": "KYfvbU4LZb0", "2": "theGrio | Black In Tech", "3": "701", "4": "theGrio"}, {"1": "ijNz7xHom8o", "2": "Being Black in Technology", "3": "10713", "4": "Du\u2019An Lightfoot"}, {"1": "z6SAjgnk9tA", "2": "African-American coder blazes trail in tech", "3": "20744", "4": "CNN Business"}, {"1": "ZCG0t8ChhPk", "2": "How I Got a Job in the Tech Industry: Black Women in Tech (Contractor VS Full Time Employee)", "3": "125", "4": "TundeModupee"}, {"1": "OmOO7MGVU7k", "2": "Black Girls Tech Summit 2019", "3": "199", "4": "Girls Talk London"}, {"1": "F3_f7sOPurI", "2": "Being a Black Man in Tech - Interview with Tech Titans Gabriel Agboruche and Sly Gittens", "3": "2896", "4": "Du\u2019An Lightfoot"}, {"1": "BQYT1X1bBfw", "2": "Uber exec: We need more black women in tech", "3": "4897", "4": "CNN Business"}, {"1": "TeBQ2OoKbQM", "2": "OHUB365- Black in Tech with Daricus Releford", "3": "17", "4": "Opportunity Hub"}, {"1": "jXXsDV1Nr3M", "2": "Sister Circle |  Tanya Sam Talks RHOA, Black Women In Tech &amp; More  | TVONE", "3": "97302", "4": "Sister Circle TV"}, {"1": "LzdNfS18SPY", "2": "Why More Non-Technical Black People Should Be Involved in Tech Companies", "3": "215", "4": "Financial Juneteenth"}, {"1": "DK_kk-Pt3ME", "2": "Being a BLACK WOMAN in Tech from a Coding Bootcamp - Am I taken seriously?", "3": "5261", "4": "livie the developer //"}, {"1": "4JO2BKgdcDs", "2": "Black Women in Technology Give Tips for Success | ESSENCE Now", "3": "18014", "4": "ESSENCE"}, {"1": "_cIvUMi4xpA", "2": "MKBHD X Brian Tong - Being Black in Tech, iPhone SE, MacBook Pro 13, 24fps vs 30fps &amp; more!", "3": "26726", "4": "Brian Tong"}, {"1": "OgEIOFZJy4M", "2": "Working in the Tech Industry in Singapore (Black in Singapore) | MFiles", "3": "7546", "4": "The Black Experience Japan"}], "2": "72299626"}, "6": {}}